dcmextras/__init__.py
dcmextras/seriesio.py
dcmextras/siemenscsa.py
dcmextras/siemensoog.py
dcmextras/siemensphoenix.py
dcmextras/version.py
dcmextras-0.3.4.data/scripts/dcm2js
dcmextras-0.3.4.dist-info/METADATA
dcmextras-0.3.4.dist-info/WHEEL
dcmextras-0.3.4.dist-info/entry_points.txt
dcmextras-0.3.4.dist-info/top_level.txt
dcmextras-0.3.4.dist-info/RECORD
