Metadata-Version: 2.1
Name: dcmextras
Version: 0.3.4
Summary: Additional dicom tools for pydicom and Siemens
Home-page: https://bitbucket.org/rtrhd/dcmextras
Download-URL: https://bitbucket.org/rtrhd/dcmextras/downloads/
Author: Ronald Hartley-Davies
Author-email: R.Hartley-Davies@physics.org
License: MIT
Classifier: Development Status :: 3 - Alpha
Classifier: Environment :: Console
Classifier: Intended Audience :: Science/Research
Classifier: Topic :: Scientific/Engineering :: Medical Science Apps.
Classifier: License :: OSI Approved :: MIT License
Classifier: Operating System :: POSIX
Classifier: Operating System :: Microsoft :: Windows
Classifier: Programming Language :: Python :: 3.8
Classifier: Programming Language :: Python :: 3.9
Classifier: Programming Language :: Python :: 3.10
Classifier: Programming Language :: Python :: 3.11
Classifier: Programming Language :: Python :: 3.12
Requires-Dist: numpy >=1.13
Requires-Dist: pydicom >=2.0
Provides-Extra: tests
Requires-Dist: nibabel ; extra == 'tests'
